odoo/addons/hr_skill/README.rst
odoo/addons/hr_skill/__init__.py
odoo/addons/hr_skill/__manifest__.py
odoo/addons/hr_skill/i18n/ar.po
odoo/addons/hr_skill/i18n/cs_CZ.po
odoo/addons/hr_skill/i18n/de.po
odoo/addons/hr_skill/i18n/en.po
odoo/addons/hr_skill/i18n/es.po
odoo/addons/hr_skill/i18n/fa.po
odoo/addons/hr_skill/i18n/fi.po
odoo/addons/hr_skill/i18n/fr.po
odoo/addons/hr_skill/i18n/gl.po
odoo/addons/hr_skill/i18n/hr.po
odoo/addons/hr_skill/i18n/hr_HR.po
odoo/addons/hr_skill/i18n/hr_skill.pot
odoo/addons/hr_skill/i18n/it.po
odoo/addons/hr_skill/i18n/lt.po
odoo/addons/hr_skill/i18n/nl_NL.po
odoo/addons/hr_skill/i18n/pl.po
odoo/addons/hr_skill/i18n/pt_BR.po
odoo/addons/hr_skill/i18n/ro.po
odoo/addons/hr_skill/i18n/sl.po
odoo/addons/hr_skill/i18n/sv.po
odoo/addons/hr_skill/migrations/11.0.2.0.0/post-migrate.py
odoo/addons/hr_skill/models/__init__.py
odoo/addons/hr_skill/models/hr_employee.py
odoo/addons/hr_skill/models/hr_employee_skill.py
odoo/addons/hr_skill/models/hr_skill.py
odoo/addons/hr_skill/readme/CONFIGURATION.rst
odoo/addons/hr_skill/readme/CONTRIBUTORS.rst
odoo/addons/hr_skill/readme/CREDITS.rst
odoo/addons/hr_skill/readme/DESCRIPTION.rst
odoo/addons/hr_skill/readme/USAGE.rst
odoo/addons/hr_skill/security/ir.model.access.csv
odoo/addons/hr_skill/static/description/icon.png
odoo/addons/hr_skill/static/description/index.html
odoo/addons/hr_skill/tests/__init__.py
odoo/addons/hr_skill/tests/test_hr_skill.py
odoo/addons/hr_skill/views/hr_employee.xml
odoo/addons/hr_skill/views/hr_employee_skill.xml
odoo/addons/hr_skill/views/hr_skill.xml
odoo11_addon_hr_skill-11.0.2.1.0.99.dev29.dist-info/METADATA
odoo11_addon_hr_skill-11.0.2.1.0.99.dev29.dist-info/WHEEL
odoo11_addon_hr_skill-11.0.2.1.0.99.dev29.dist-info/top_level.txt
odoo11_addon_hr_skill-11.0.2.1.0.99.dev29.dist-info/RECORD
